LICENSE
README.md
setup.py
cachettl/__init__.py
cachettl/cachettl.py
cachettl.egg-info/PKG-INFO
cachettl.egg-info/SOURCES.txt
cachettl.egg-info/dependency_links.txt
cachettl.egg-info/not-zip-safe
cachettl.egg-info/top_level.txt