Metadata-Version: 2.1
Name: cachettl
Version: 1.0.3
Summary: cachettl is an elegant LRU TTL cache decorator that also works with asyncio. It has the cache_info(), cache_clear() methods and access to the remainingttl property.
Home-page: https://github.com/rabuchaim/cachettl
Author: Ricardo Abuchaim
Author-email: ricardoabuchaim@gmail.com
Maintainer: Ricardo Abuchaim
Maintainer-email: ricardoabuchaim@gmail.com
License: MIT
Project-URL: Issue Tracker, https://github.com/rabuchaim/cachettl/issues
Project-URL: Source code, https://github.com/rabuchaim/cachettl
Keywords: cachettl,cache_ttl,ttlcache,async cache ttl,async_cachettl,functools,lrucache,lru_cache,cache,pure-python,purepython,pure python
Classifier: Development Status :: 5 - Production/Stable
Classifier: Topic :: Software Development :: Libraries
Classifier: Topic :: Software Development :: Libraries :: Python Modules
Classifier: Topic :: Utilities
Classifier: Intended Audience :: Developers
Classifier: Intended Audience :: Information Technology
Classifier: Intended Audience :: System Administrators
Classifier: Operating System :: MacOS
Classifier: Operating System :: Microsoft :: Windows :: Windows 10
Classifier: Operating System :: Microsoft :: Windows :: Windows 11
Classifier: Operating System :: Unix
Classifier: Operating System :: POSIX
Classifier: Operating System :: POSIX :: Linux
Classifier: Operating System :: POSIX :: BSD
Classifier: Operating System :: POSIX :: BSD :: FreeBSD
Classifier: Programming Language :: Python
Classifier: Programming Language :: Python :: 3
Classifier: Programming Language :: Python :: 3.7
Classifier: Programming Language :: Python :: 3.8
Classifier: Programming Language :: Python :: 3.9
Classifier: Programming Language :: Python :: 3.10
Classifier: Programming Language :: Python :: 3.11
Classifier: Programming Language :: Python :: 3.12
Classifier: Programming Language :: Python :: 3.13
Classifier: Programming Language :: Python :: Implementation :: PyPy
Classifier: License :: OSI Approved :: MIT License
Requires-Python: >=3.7
License-File: LICENSE
